skeraton/__init__.py
skeraton/skeraton.py
skeraton-0.1.0.dist-info/LICENSE
skeraton-0.1.0.dist-info/METADATA
skeraton-0.1.0.dist-info/WHEEL
skeraton-0.1.0.dist-info/top_level.txt
skeraton-0.1.0.dist-info/RECORD
