Metadata-Version: 2.1
Name: skeraton
Version: 0.1.0
Summary: Keras implementation of skeleton transformer module
Home-page: https://github.com/Yutsuro/skeleton-transformer-Keras
Author: Yutsuro
Author-email: Yuki@utsu.ro
License: MIT
Keywords: Skeleton-Transformer Python Keras Action-Recognition Skeleton Pose-Estimation
Classifier: License :: OSI Approved :: MIT License
Classifier: Programming Language :: Python :: 3
Classifier: Programming Language :: Python :: 3.6
Classifier: Programming Language :: Python :: 3.7
Classifier: Programming Language :: Python :: 3.8
Classifier: Programming Language :: Python :: 3.9
Classifier: Programming Language :: Python :: 3 :: Only
Classifier: Topic :: Software Development :: Libraries :: Python Modules
License-File: LICENSE
Requires-Dist: keras (==2.11.0)
